audioldm2/__init__.py
audioldm2/pipeline.py
audioldm2/utils.py
audioldm2/audiomae_gen/__init__.py
audioldm2/audiomae_gen/sequence_input.py
audioldm2/audiomae_gen/utils.py
audioldm2/clap/__init__.py
audioldm2/clap/open_clip/__init__.py
audioldm2/clap/open_clip/bpe_simple_vocab_16e6.txt.gz
audioldm2/clap/open_clip/factory.py
audioldm2/clap/open_clip/feature_fusion.py
audioldm2/clap/open_clip/htsat.py
audioldm2/clap/open_clip/loss.py
audioldm2/clap/open_clip/model.py
audioldm2/clap/open_clip/openai.py
audioldm2/clap/open_clip/pann_model.py
audioldm2/clap/open_clip/pretrained.py
audioldm2/clap/open_clip/timm_model.py
audioldm2/clap/open_clip/tokenizer.py
audioldm2/clap/open_clip/transform.py
audioldm2/clap/open_clip/utils.py
audioldm2/clap/open_clip/model_configs/HTSAT-base.json
audioldm2/clap/open_clip/model_configs/HTSAT-large.json
audioldm2/clap/open_clip/model_configs/HTSAT-tiny-win-1536.json
audioldm2/clap/open_clip/model_configs/HTSAT-tiny.json
audioldm2/clap/open_clip/model_configs/PANN-10.json
audioldm2/clap/open_clip/model_configs/PANN-14-fmax-18k.json
audioldm2/clap/open_clip/model_configs/PANN-14-fmax-8k-20s.json
audioldm2/clap/open_clip/model_configs/PANN-14-tiny-transformer.json
audioldm2/clap/open_clip/model_configs/PANN-14-win-1536.json
audioldm2/clap/open_clip/model_configs/PANN-14.json
audioldm2/clap/open_clip/model_configs/PANN-6.json
audioldm2/clap/open_clip/model_configs/RN101-quickgelu.json
audioldm2/clap/open_clip/model_configs/RN101.json
audioldm2/clap/open_clip/model_configs/RN50-quickgelu.json
audioldm2/clap/open_clip/model_configs/RN50.json
audioldm2/clap/open_clip/model_configs/RN50x16.json
audioldm2/clap/open_clip/model_configs/RN50x4.json
audioldm2/clap/open_clip/model_configs/ViT-B-16.json
audioldm2/clap/open_clip/model_configs/ViT-B-32-quickgelu.json
audioldm2/clap/open_clip/model_configs/ViT-B-32.json
audioldm2/clap/open_clip/model_configs/ViT-L-14.json
audioldm2/clap/training/__init__.py
audioldm2/clap/training/audioset_textmap.npy
audioldm2-0.1.0.dist-info/LICENSE
audioldm2-0.1.0.dist-info/METADATA
audioldm2-0.1.0.dist-info/WHEEL
audioldm2-0.1.0.dist-info/top_level.txt
audioldm2-0.1.0.dist-info/RECORD
