Metadata-Version: 2.1
Name: audioldm2
Version: 0.1.0
Summary: This package is written for text-to-audio/music generation.
Home-page: https://github.com/haoheliu/audioldm2
Author: Haohe Liu
Author-email: haoheliu@gmail.com
License: MIT
Classifier: License :: OSI Approved :: MIT License
Classifier: Programming Language :: Python
Classifier: Programming Language :: Python :: 3
Classifier: Programming Language :: Python :: 3.7
Classifier: Programming Language :: Python :: Implementation :: CPython
Classifier: Programming Language :: Python :: Implementation :: PyPy
Requires-Python: >=3.7.0
License-File: LICENSE
Requires-Dist: torch (>=1.13.0)
Requires-Dist: torchaudio (>=0.13.0)
Requires-Dist: torchvision (>=0.14.0)
Requires-Dist: tqdm
Requires-Dist: gradio
Requires-Dist: pyyaml
Requires-Dist: einops
Requires-Dist: chardet
Requires-Dist: numpy (<=1.23.5)
Requires-Dist: soundfile
Requires-Dist: librosa (==0.9.2)
Requires-Dist: scipy
Requires-Dist: pandas
Requires-Dist: unidecode
Requires-Dist: phonemizer
Requires-Dist: torchlibrosa (>=0.0.9)
Requires-Dist: transformers (==4.30.2)
Requires-Dist: huggingface-hub
Requires-Dist: progressbar
Requires-Dist: ftfy
Requires-Dist: timm
